ironleapdjango/__init__.py
ironleapdjango/apiclient.py
ironleapdjango/job_scheduler.py
ironleapdjango/logger_helper.py
ironleapdjango/masks.py
ironleapdjango/middleware.py
ironleapdjango/parse_body.py
ironleapdjango/schemas.py
ironleapdjango-1.1.1.dist-info/METADATA
ironleapdjango-1.1.1.dist-info/WHEEL
ironleapdjango-1.1.1.dist-info/top_level.txt
ironleapdjango-1.1.1.dist-info/RECORD
