Metadata-Version: 2.1
Name: ironleapdjango
Version: 1.1.1
Summary: Iron Leap Django SDK
Home-page: https://ironleap.io
Author: Iron Leap Inc.
Author-email: founders@ironleap.io
License: UNKNOWN
Platform: UNKNOWN
Requires-Dist: requests
Requires-Dist: jsonpickle
Requires-Dist: python-dateutil
Requires-Dist: apscheduler
